SelfHealing/__init__.py
SelfHealing/appium_healing.py
SelfHealing/browser_healing.py
SelfHealing/llm_client.py
SelfHealing/locator_db.py
SelfHealing/SelfHealing.py
SelfHealing/template.html
SelfHealing/utils.py
SelfHealing/visual_healing.py
robotframework_heal-0.3.0.dev2.dist-info/LICENSE
robotframework_heal-0.3.0.dev2.dist-info/METADATA
robotframework_heal-0.3.0.dev2.dist-info/WHEEL
robotframework_heal-0.3.0.dev2.dist-info/RECORD
