Metadata-Version: 2.3
Name: robotframework-heal
Version: 0.3.0.dev2
Summary: A Robot Framework Listener for library agnostic self-healing and smart recovery of tests
License: Apache-2.0
Author: Many Kasiriha
Author-email: many.kasiriha@dbschenker.com
Maintainer: Many Kasiriha
Maintainer-email: many.kasiriha@dbschenker.com
Requires-Python: >=3.10,<4.0
Classifier: License :: OSI Approved :: Apache Software License
Classifier: Programming Language :: Python :: 3
Classifier: Programming Language :: Python :: 3.10
Classifier: Programming Language :: Python :: 3.11
Classifier: Programming Language :: Python :: 3.12
Classifier: Programming Language :: Python :: 3.13
Requires-Dist: beautifulsoup4
Requires-Dist: cssify
Requires-Dist: jinja2
Requires-Dist: litellm
Requires-Dist: lxml
Requires-Dist: opencv-python-headless
Requires-Dist: parsimonious
Requires-Dist: pyautogui
Requires-Dist: python-dotenv
Requires-Dist: robotframework
Requires-Dist: robotframework-appiumlibrary
Requires-Dist: robotframework-browser
Requires-Dist: thefuzz
Requires-Dist: tinydb
Project-URL: Homepage, https://github.com/manykarim/robotframework-heal
